setup.cfg
setup.py
redmine_auth.egg-info/PKG-INFO
redmine_auth.egg-info/SOURCES.txt
redmine_auth.egg-info/dependency_links.txt
redmine_auth.egg-info/entry_points.txt
redmine_auth.egg-info/not-zip-safe
redmine_auth.egg-info/requires.txt
redmine_auth.egg-info/top_level.txt
redmineauth/__init__.py
redmineauth/jenkins.py
redmineauth/main.py
redmineauth/redmineauth.py