Metadata-Version: 1.0
Name: redmine-auth
Version: 0.3.0
Summary: Subversion/Jenkins Authentication Through Redmine
Home-page: https://github.com/laiyonghao/redmine-auth
Author: LaiYonghao
Author-email: mail@laiyonghao.com
License: MIT
Keywords: apache,apache2,redmine,auth,svn,subversion
Platform: UNKNOWN
